<SCREEN>
    <GRIDMESH>
        <GRIDX>3</GRIDX>
        <GRIDY>3</GRIDY>
    </GRIDMESH>
    <BOUNDINGBOX>
        <ulx>0.001000</ulx>
        <uly>0.000000</uly>
        <lrx>1.000000</lrx>
        <lry>1.000000</lry>
    </BOUNDINGBOX>
    <POINT>
        <X>315.000000</X>
        <Y>200.000000</Y>
    </POINT>
    <POINT>
        <X>230.000000</X>
        <Y>201.000000</Y>
    </POINT>
    <POINT>
        <X>136.000000</X>
        <Y>197.000000</Y>
    </POINT>
    <POINT>
        <X>37.000000</X>
        <Y>148.000000</Y>
    </POINT>
    <POINT>
        <X>309.000000</X>
        <Y>151.000000</Y>
    </POINT>
    <POINT>
        <X>226.000000</X>
        <Y>143.000000</Y>
    </POINT>
    <POINT>
        <X>137.000000</X>
        <Y>139.000000</Y>
    </POINT>
    <POINT>
        <X>51.000000</X>
        <Y>134.000000</Y>
    </POINT>
    <POINT>
        <X>298.000000</X>
        <Y>99.000000</Y>
    </POINT>
    <POINT>
        <X>236.000000</X>
        <Y>93.000000</Y>
    </POINT>
    <POINT>
        <X>145.000000</X>
        <Y>87.000000</Y>
    </POINT>
    <POINT>
        <X>66.000000</X>
        <Y>83.000000</Y>
    </POINT>
    <POINT>
        <X>292.000000</X>
        <Y>42.000000</Y>
    </POINT>
    <POINT>
        <X>223.000000</X>
        <Y>36.000000</Y>
    </POINT>
    <POINT>
        <X>142.000000</X>
        <Y>33.000000</Y>
    </POINT>
    <POINT>
        <X>72.000000</X>
        <Y>36.000000</Y>
    </POINT>
</SCREEN>
<WARP>
    <BOTTOMLEFT>
        <X>0.000000</X>
        <Y>240.000000</Y>
    </BOTTOMLEFT>
    <BOTTOMRIGHT>
        <X>320.000000</X>
        <Y>240.000000</Y>
    </BOTTOMRIGHT>
    <TOPRIGHT>
        <X>320.000000</X>
        <Y>0.000000</Y>
    </TOPRIGHT>
    <TOPLEFT>
        <X>0.000000</X>
        <Y>0.000000</Y>
    </TOPLEFT>
</WARP>
